heatcal/__init__.py
heatcal-0.0.1.dist-info/LICENSE.txt
heatcal-0.0.1.dist-info/METADATA
heatcal-0.0.1.dist-info/WHEEL
heatcal-0.0.1.dist-info/top_level.txt
heatcal-0.0.1.dist-info/RECORD
