Metadata-Version: 2.1
Name: heatcal
Version: 0.0.1
Summary: A package to easily generate calendar heatmaps
Author-email: Patrick Holzer <patrick.projects@gmx.de>
Project-URL: Homepage, https://github.com/pypa/sampleproject
Project-URL: Issues, https://github.com/pypa/sampleproject/issues
Classifier: Programming Language :: Python :: 3
Classifier: License :: OSI Approved :: MIT License
Classifier: Operating System :: OS Independent
Requires-Python: >=3.8
License-File: LICENSE.txt
Requires-Dist: tomli ; python_version < "3.11"
